NlpHub/NlpHub.py
NlpHub/__init__.py
NlpHub-1.0.3.dist-info/LICENSE
NlpHub-1.0.3.dist-info/METADATA
NlpHub-1.0.3.dist-info/WHEEL
NlpHub-1.0.3.dist-info/top_level.txt
NlpHub-1.0.3.dist-info/RECORD
